conceptnet_lite/__init__.py
conceptnet_lite/db.py
conceptnet_lite/utils.py
conceptnet_lite-0.2.0.dist-info/LICENSE
conceptnet_lite-0.2.0.dist-info/METADATA
conceptnet_lite-0.2.0.dist-info/WHEEL
conceptnet_lite-0.2.0.dist-info/RECORD
