Metadata-Version: 2.1
Name: conceptnet-lite
Version: 0.2.0
Summary: Python library to work with ConceptNet offline without the need of PostgreSQL
Home-page: https://github.com/ldtoolkit/conceptnet-lite
License: Apache-2.0
Author: Roman Inflianskas
Author-email: infroma@gmail.com
Requires-Python: >=3.8,<4.0
Classifier: Development Status :: 7 - Inactive
Classifier: License :: OSI Approved :: Apache Software License
Classifier: Programming Language :: Python :: 3
Classifier: Programming Language :: Python :: 3.8
Classifier: Programming Language :: Python :: 3.9
Classifier: Programming Language :: Python :: 3.10
Classifier: Programming Language :: Python :: 3.11
Classifier: Programming Language :: Python :: 3.12
Requires-Dist: lmdb (>=1.0,<2.0)
Requires-Dist: peewee (>=3.10,<4.0)
Requires-Dist: pysmartdl (>=1.3,<2.0)
Requires-Dist: tqdm (>=4.35,<5.0)
Project-URL: Repository, https://github.com/ldtoolkit/conceptnet-lite
